mcp_server_websearch/__init__.py
mcp_server_websearch/__main__.py
mcp_server_websearch/server.py
mcp_server_websearch-0.1.9.dist-info/METADATA
mcp_server_websearch-0.1.9.dist-info/WHEEL
mcp_server_websearch-0.1.9.dist-info/entry_points.txt
mcp_server_websearch-0.1.9.dist-info/RECORD
