Metadata-Version: 2.4
Name: mcp-server-websearch
Version: 0.1.9
Summary: A MCP server for websearch
Author-email: UnieAI Eric <chouwei88929@gmail.com>
Classifier: Development Status :: 4 - Beta
Classifier: Intended Audience :: Developers
Classifier: License :: OSI Approved :: MIT License
Classifier: Programming Language :: Python :: 3
Classifier: Programming Language :: Python :: 3.10
Requires-Python: >=3.10
Requires-Dist: mcp>=1.0.0
Requires-Dist: pydantic>=2.0.0
Requires-Dist: tzdata>=2024.2
